webimgui/__init__.py
webimgui/components.py
webimgui/exceptions.py
webimgui/logging.py
webimgui/page.py
webimgui/serve.py
webimgui/session.py
webimgui/ui.py
webimgui/dist/favicon.ico
webimgui/dist/index.html
webimgui/dist/manifest.json
webimgui/dist/precache-manifest.2728b2ebd0af9eca0726063d6b5f433b.js
webimgui/dist/precache-manifest.d815db4783fa0297543da8f1cb4a23cf.js
webimgui/dist/precache-manifest.fdf7b78d368991a5bfc5fbc6abb5b00c.js
webimgui/dist/robots.txt
webimgui/dist/service-worker.js
webimgui/dist/css/app.541d3088.css
webimgui/dist/css/chunk-0e4bc198.80af37b8.css
webimgui/dist/css/chunk-2fcd62eb.d08d4426.css
webimgui/dist/css/chunk-3cc2bb65.379cc966.css
webimgui/dist/css/chunk-469d02a5.4567d0e4.css
webimgui/dist/css/chunk-4c49ee47.d3560f52.css
webimgui/dist/css/chunk-51f6fc91.765de98c.css
webimgui/dist/css/chunk-6e1119e9.d1a2c137.css
webimgui/dist/css/chunk-7b2b4dba.c235a120.css
webimgui/dist/css/chunk-7f343098.82ec2ce5.css
webimgui/dist/css/chunk-d749c05c.70c456e2.css
webimgui/dist/css/chunk-vendors.7c788ae1.css
webimgui/dist/img/icons/android-chrome-192x192.png
webimgui/dist/img/icons/android-chrome-512x512.png
webimgui/dist/img/icons/apple-touch-icon-120x120.png
webimgui/dist/img/icons/apple-touch-icon-152x152.png
webimgui/dist/img/icons/apple-touch-icon-180x180.png
webimgui/dist/img/icons/apple-touch-icon-60x60.png
webimgui/dist/img/icons/apple-touch-icon-76x76.png
webimgui/dist/img/icons/apple-touch-icon.png
webimgui/dist/img/icons/favicon-16x16.png
webimgui/dist/img/icons/favicon-32x32.png
webimgui/dist/img/icons/msapplication-icon-144x144.png
webimgui/dist/img/icons/mstile-150x150.png
webimgui/dist/img/icons/safari-pinned-tab.svg
webimgui/dist/js/app.758921a2.js
webimgui/dist/js/app.758921a2.js.map
webimgui/dist/js/app.ad70e236.js
webimgui/dist/js/app.ad70e236.js.map
webimgui/dist/js/app.ea1888ac.js
webimgui/dist/js/app.ea1888ac.js.map
webimgui/dist/js/chunk-0e4bc198.d5d68e7b.js
webimgui/dist/js/chunk-0e4bc198.d5d68e7b.js.map
webimgui-0.0.2.dist-info/LICENSE
webimgui-0.0.2.dist-info/METADATA
webimgui-0.0.2.dist-info/WHEEL
webimgui-0.0.2.dist-info/top_level.txt
webimgui-0.0.2.dist-info/RECORD
